{
    "runways":
    [
		{
			"name": "runway1",
			"res": "Runway1.png",
			"centerx": 20,
			"centery": 20,
			"radius": 20
		},
		{
			"name": "runway2",
			"res": "Runway2.png",
			"centerx": 23,
			"centery": 23,
			"radius": 25
		}
    ],
	"aircrafts":
	[
		{
			"name": "yellow",
			"res": "Aircraft1.png",
			"radius": 35,
			"speed": 120,
			"turn": 1.75,
			"runways": ["runway1", "runway2"]
		},
		{
			"name": "red",
			"res": "Aircraft2.png",
			"radius": 35,
			"speed": 120,
			"turn": 1.75,
			"runways": ["runway1", "runway2"]
		},
		{
			"name": "purple",
			"res": "Aircraft3.png",
			"radius": 35,
			"speed": 120,
			"turn": 1.75,
			"runways": ["runway1", "runway2"]
		},
		{
			"name": "small",
			"res": "Aircraft4.png",
			"radius": 23,
			"speed": 80,
			"turn": 2,
			"runways": ["runway1", "runway2"]
		}
	],
	"explosions":
	[
        {
            "name": "exp1",
            "res": "Exp2.png",
            "radius": 128,
            "time": 3.0
        }
	]
}
